http_tools/__init__.py
http_tools/__main__.py
http_tools/settings.py
http_tools/modules/__init__.py
http_tools/modules/capture.py
http_tools/modules/interceptor.py
http_tools/modules/runner.py
http_tools/web/__init__.py
http_tools/web/flow_tools.py
http_tools/web/server.py
http_tools/web/assets/static/css/AdminLTE.min.css
http_tools/web/assets/static/css/bootstrap.min.css
http_tools/web/assets/static/css/font-awesome.min.css
http_tools/web/assets/static/css/ionicons.min.css
http_tools/web/assets/static/css/jquery.growl.css
http_tools/web/assets/static/css/style.css
http_tools/web/assets/static/css/sweetalert2.min.css
http_tools/web/assets/static/css/skins/_all-skins.css
http_tools/web/assets/static/css/skins/_all-skins.min.css
http_tools/web/assets/static/css/skins/skin-black-light.css
http_tools/web/assets/static/css/skins/skin-black-light.min.css
http_tools/web/assets/static/css/skins/skin-black.css
http_tools/web/assets/static/css/skins/skin-black.min.css
http_tools/web/assets/static/css/skins/skin-blue-light.css
http_tools/web/assets/static/css/skins/skin-blue-light.min.css
http_tools/web/assets/static/css/skins/skin-blue.css
http_tools/web/assets/static/css/skins/skin-blue.min.css
http_tools/web/assets/static/css/skins/skin-green-light.css
http_tools/web/assets/static/css/skins/skin-green-light.min.css
http_tools/web/assets/static/css/skins/skin-green.css
http_tools/web/assets/static/css/skins/skin-green.min.css
http_tools/web/assets/static/css/skins/skin-purple-light.css
http_tools/web/assets/static/css/skins/skin-purple-light.min.css
http_tools/web/assets/static/css/skins/skin-purple.css
http_tools/web/assets/static/css/skins/skin-purple.min.css
http_tools/web/assets/static/css/skins/skin-red-light.css
http_tools/web/assets/static/css/skins/skin-red-light.min.css
http_tools/web/assets/static/css/skins/skin-red.css
http_tools/web/assets/static/css/skins/skin-red.min.css
http_tools/web/assets/static/css/skins/skin-yellow-light.css
http_tools-2.0.0.dist-info/LICENSE.txt
http_tools-2.0.0.dist-info/METADATA
http_tools-2.0.0.dist-info/WHEEL
http_tools-2.0.0.dist-info/entry_points.txt
http_tools-2.0.0.dist-info/top_level.txt
http_tools-2.0.0.dist-info/RECORD
