Metadata-Version: 2.1
Name: http-tools
Version: 2.0.0
Summary: httptools helps you to capture, repeat and live intercept HTTP requests. It is built on top of [mitmproxy](https://mitmproxy.org/)
Home-page: https://github.com/MobSF/httptools
Author: Ajin Abraham
Author-email: ajin25@gmail.com
License: GPL v3
Platform: UNKNOWN
Classifier: Development Status :: 4 - Beta
Classifier: Intended Audience :: Developers
Classifier: License :: OSI Approved :: GNU Lesser General Public License v2 (LGPLv2)
Classifier: Programming Language :: Python :: 3.6
Requires-Dist: mitmproxy (==5.3.0)
